pipw/__init__.py
pipw/main.py
pipw-1.0.5.dist-info/DESCRIPTION.rst
pipw-1.0.5.dist-info/METADATA
pipw-1.0.5.dist-info/RECORD
pipw-1.0.5.dist-info/WHEEL
pipw-1.0.5.dist-info/entry_points.txt
pipw-1.0.5.dist-info/metadata.json
pipw-1.0.5.dist-info/top_level.txt
