Metadata-Version: 2.0
Name: pipw
Version: 1.0.5
Summary: A wrapper for pip to save packages in requirements files.
Home-page: https://github.com/danielzk/pipw
Author: Daniel Ramos
Author-email: danielrz@protonmail.com
License: MIT
Keywords: pip save requirements npm
Platform: UNKNOWN
Classifier: Programming Language :: Python :: 3.6
Classifier: Programming Language :: Python :: 3.5
Classifier: Programming Language :: Python :: 3.4
Classifier: Programming Language :: Python :: 3.3
Classifier: Programming Language :: Python :: 2.7
Classifier: Topic :: Software Development :: Libraries
Classifier: Topic :: Utilities
Classifier: License :: OSI Approved :: MIT License
Requires-Dist: click (~=6.7)
Requires-Dist: pyyaml (~=3.12)
